wasm_test_widget/__init__.py
wasm_test_widget/widget.py
wasm_test_widget/labextension/package.json
wasm_test_widget/labextension/static/122.e9ed10395024aa714631.js
wasm_test_widget/labextension/static/509.a8bb7ce7f7435c2a4248.js
wasm_test_widget/labextension/static/726.268eeeb840d150c4d5d4.js
wasm_test_widget/labextension/static/e5c75055ce5ef0118de7.wasm
wasm_test_widget/labextension/static/remoteEntry.d5675b03aa541f08f8eb.js
wasm_test_widget/labextension/static/style.js
wasm_test_widget/labextension/static/third-party-licenses.json
wasm_test_widget/nbextension/18b9864450e58aed6ae5.wasm
wasm_test_widget/nbextension/index.js
wasm_test_widget-0.1.0.dev0.data/data/share/jupyter/labextensions/wasm_test_widget/package.json
wasm_test_widget-0.1.0.dev0.data/data/share/jupyter/labextensions/wasm_test_widget/static/122.e9ed10395024aa714631.js
wasm_test_widget-0.1.0.dev0.data/data/share/jupyter/labextensions/wasm_test_widget/static/509.a8bb7ce7f7435c2a4248.js
wasm_test_widget-0.1.0.dev0.data/data/share/jupyter/labextensions/wasm_test_widget/static/726.268eeeb840d150c4d5d4.js
wasm_test_widget-0.1.0.dev0.data/data/share/jupyter/labextensions/wasm_test_widget/static/e5c75055ce5ef0118de7.wasm
wasm_test_widget-0.1.0.dev0.data/data/share/jupyter/labextensions/wasm_test_widget/static/remoteEntry.d5675b03aa541f08f8eb.js
wasm_test_widget-0.1.0.dev0.data/data/share/jupyter/labextensions/wasm_test_widget/static/style.js
wasm_test_widget-0.1.0.dev0.data/data/share/jupyter/labextensions/wasm_test_widget/static/third-party-licenses.json
wasm_test_widget-0.1.0.dev0.data/data/share/jupyter/nbextensions/wasm_test_widget/18b9864450e58aed6ae5.wasm
wasm_test_widget-0.1.0.dev0.data/data/share/jupyter/nbextensions/wasm_test_widget/index.js
wasm_test_widget-0.1.0.dev0.data/data/etc/jupyter/nbconfig/notebook.d/wasm_test_widget.json
wasm_test_widget-0.1.0.dev0.data/data/share/jupyter/labextensions/wasm_test_widget/install.json
wasm_test_widget-0.1.0.dev0.dist-info/METADATA
wasm_test_widget-0.1.0.dev0.dist-info/WHEEL
wasm_test_widget-0.1.0.dev0.dist-info/licenses/LICENSE.md
wasm_test_widget-0.1.0.dev0.dist-info/RECORD
