Metadata-Version: 2.4
Name: wasm_test_widget
Version: 0.1.0.dev0
Summary: A Custom Jupyter Widget Library
Project-URL: Homepage, https://github.com/Twinklebear/wasm_test_widget
Author-email: Will Usher <will@luminarycloud.com>
License: The MIT License (MIT)
License-File: LICENSE.md
Keywords: IPython,Jupyter,Widgets
Requires-Python: >=3.9
Requires-Dist: ipywidgets>=8.0.0
